{
	"country_code": "CN",
	"parent_id": "CN-22-59b6cf",
	"locale": "zh-Latn",
	"subdivisions": {
		"CN-22-59b6cf-0ef3c6": {
			"code": "东丰县",
			"name": "Dongfeng Xian",
			"translations": {
				"zh": {
					"name": "东丰县"
				}
			}
		},
		"CN-22-59b6cf-3fba39": {
			"code": "东辽县",
			"name": "Dongliao Xian",
			"translations": {
				"zh": {
					"name": "东辽县"
				}
			}
		},
		"CN-22-59b6cf-a520b8": {
			"code": "龙山区",
			"name": "Longshan Qu",
			"translations": {
				"zh": {
					"name": "龙山区"
				}
			}
		},
		"CN-22-59b6cf-5f7d0f": {
			"code": "西安区",
			"name": "Xi'an Qu",
			"translations": {
				"zh": {
					"name": "西安区"
				}
			}
		}
	}
}