{
	"country_code": "CN",
	"parent_id": "CN-63-c0c513",
	"locale": "zh-Latn",
	"subdivisions": {
		"CN-63-c0c513-f73ce7": {
			"code": "刚察县",
			"name": "Gangca Xian",
			"translations": {
				"zh": {
					"name": "刚察县"
				}
			}
		},
		"CN-63-c0c513-ae8199": {
			"code": "海晏县",
			"name": "Haiyan Xian",
			"translations": {
				"zh": {
					"name": "海晏县"
				}
			}
		},
		"CN-63-c0c513-8d7073": {
			"code": "门源回族自治县",
			"name": "Menyuan Xian",
			"translations": {
				"zh": {
					"name": "门源县"
				}
			}
		},
		"CN-63-c0c513-e1e6d3": {
			"code": "祁连县",
			"name": "Qilian Xian",
			"translations": {
				"zh": {
					"name": "祁连县"
				}
			}
		}
	}
}