{
	"country_code": "KR",
	"parent_id": "KR-41-dd67e3",
	"locale": "ko-Latn",
	"subdivisions": {
		"KR-41-dd67e3-04b882": {
			"code": "권선구",
			"name": "Gwonseon-gu",
			"postal_code_pattern": "16[3-6]|441",
			"translations": {
				"ko": {
					"name": "권선구"
				}
			}
		},
		"KR-41-dd67e3-fabdd3": {
			"code": "영통구",
			"name": "Yeongtong-gu",
			"postal_code_pattern": "16[245-7]|443",
			"translations": {
				"ko": {
					"name": "영통구"
				}
			}
		},
		"KR-41-dd67e3-fd0046": {
			"code": "장안구",
			"name": "Jangan-gu",
			"postal_code_pattern": "16[2-4]|440",
			"translations": {
				"ko": {
					"name": "장안구"
				}
			}
		},
		"KR-41-dd67e3-015162": {
			"code": "팔달구",
			"name": "Paldal-gu",
			"postal_code_pattern": "16[2-6]|442",
			"translations": {
				"ko": {
					"name": "팔달구"
				}
			}
		}
	}
}