{
    "MY-01": {
        "locale": "ms",
        "country_code": "MY",
        "parent_id": null,
        "id": "MY-01",
        "code": "JOHOR",
        "name": "JOHOR",
        "postal_code_pattern": "8[0-6]"
    },
    "MY-02": {
        "locale": "ms",
        "country_code": "MY",
        "parent_id": null,
        "id": "MY-02",
        "code": "KEDAH",
        "name": "KEDAH",
        "postal_code_pattern": "0[5-9]|34950"
    },
    "MY-03": {
        "locale": "ms",
        "country_code": "MY",
        "parent_id": null,
        "id": "MY-03",
        "code": "KELANTAN",
        "name": "KELANTAN",
        "postal_code_pattern": "1[5-9]"
    },
    "MY-14": {
        "locale": "ms",
        "country_code": "MY",
        "parent_id": null,
        "id": "MY-14",
        "code": "KUALA LUMPUR",
        "name": "KUALA LUMPUR",
        "postal_code_pattern": "5|60"
    },
    "MY-15": {
        "locale": "ms",
        "country_code": "MY",
        "parent_id": null,
        "id": "MY-15",
        "code": "LABUAN",
        "name": "LABUAN",
        "postal_code_pattern": "87"
    },
    "MY-04": {
        "locale": "ms",
        "country_code": "MY",
        "parent_id": null,
        "id": "MY-04",
        "code": "MELAKA",
        "name": "MELAKA",
        "postal_code_pattern": "7[5-9]"
    },
    "MY-05": {
        "locale": "ms",
        "country_code": "MY",
        "parent_id": null,
        "id": "MY-05",
        "code": "NEGERI SEMBILAN",
        "name": "NEGERI SEMBILAN",
        "postal_code_pattern": "7[0-4]"
    },
    "MY-06": {
        "locale": "ms",
        "country_code": "MY",
        "parent_id": null,
        "id": "MY-06",
        "code": "PAHANG",
        "name": "PAHANG",
        "postal_code_pattern": "2[5-8]|39|49|69"
    },
    "MY-08": {
        "locale": "ms",
        "country_code": "MY",
        "parent_id": null,
        "id": "MY-08",
        "code": "PERAK",
        "name": "PERAK",
        "postal_code_pattern": "3[0-6]|39000"
    },
    "MY-09": {
        "locale": "ms",
        "country_code": "MY",
        "parent_id": null,
        "id": "MY-09",
        "code": "PERLIS",
        "name": "PERLIS",
        "postal_code_pattern": "0[12]"
    },
    "MY-07": {
        "locale": "ms",
        "country_code": "MY",
        "parent_id": null,
        "id": "MY-07",
        "code": "PULAU PINANG",
        "name": "PULAU PINANG",
        "postal_code_pattern": "1[0-4]"
    },
    "MY-16": {
        "locale": "ms",
        "country_code": "MY",
        "parent_id": null,
        "id": "MY-16",
        "code": "PUTRAJAYA",
        "name": "PUTRAJAYA",
        "postal_code_pattern": "62"
    },
    "MY-12": {
        "locale": "ms",
        "country_code": "MY",
        "parent_id": null,
        "id": "MY-12",
        "code": "SABAH",
        "name": "SABAH",
        "postal_code_pattern": "8[89]|9[01]"
    },
    "MY-13": {
        "locale": "ms",
        "country_code": "MY",
        "parent_id": null,
        "id": "MY-13",
        "code": "SARAWAK",
        "name": "SARAWAK",
        "postal_code_pattern": "9[3-8]"
    },
    "MY-10": {
        "locale": "ms",
        "country_code": "MY",
        "parent_id": null,
        "id": "MY-10",
        "code": "SELANGOR",
        "name": "SELANGOR",
        "postal_code_pattern": "4[0-8]|6[3-8]"
    },
    "MY-11": {
        "locale": "ms",
        "country_code": "MY",
        "parent_id": null,
        "id": "MY-11",
        "code": "TERENGGANU",
        "name": "TERENGGANU",
        "postal_code_pattern": "2[0-4]"
    }
}